retroperm/__init__.py
retroperm/project.py
retroperm/setup.py
retroperm/analysis/__init__.py
retroperm/analysis/functions.py
retroperm/analysis/permfinder.py
retroperm/analysis/resolver.py
retroperm/analysis/utils.py
retroperm/analysis/utils_angrmgmt.py
retroperm/rules/__init__.py
retroperm/rules/argument_rule.py
retroperm/rules/ban_category_rule.py
retroperm/rules/ban_library_function_rule.py
retroperm/rules/data.py
retroperm/rules/default_rules.py
retroperm/rules/filesystem_rule.py
retroperm/rules/pathrules.py
retroperm/rules/rule.py
retroperm/rules/ruleList.py
retroperm/rules/rules.py
retroperm-0.1.3.dist-info/LICENSE
retroperm-0.1.3.dist-info/METADATA
retroperm-0.1.3.dist-info/WHEEL
retroperm-0.1.3.dist-info/top_level.txt
retroperm-0.1.3.dist-info/RECORD
