Metadata-Version: 2.1
Name: retroperm
Version: 0.1.3
Summary: A retroactive effective binary permission deduction tool
Home-page: https://github.com/SpiritSeal/retroperm
Author-email: Saketh Reddy <yssaketh@gmail.com>
License: MIT
Project-URL: Homepage, https://github.com/SpiritSeal/retroperm
Project-URL: Bug Tracker, https://github.com/SpiritSeal/retroperm/issues
Classifier: Programming Language :: Python :: 3
Classifier: License :: OSI Approved :: GNU Lesser General Public License v3 or later (LGPLv3+)
Classifier: Operating System :: OS Independent
Requires-Python: >=3.7
License-File: LICENSE
Requires-Dist: angr
Requires-Dist: pathlib2
Requires-Dist: sortedcollections
